my_package/__init__.py
my_package/greetings.py
anabih_python_test-24.0.0.dist-info/METADATA
anabih_python_test-24.0.0.dist-info/WHEEL
anabih_python_test-24.0.0.dist-info/top_level.txt
anabih_python_test-24.0.0.dist-info/RECORD
